curc/__init__.py
curc/__main__.py
curc-1.0.14.dist-info/METADATA
curc-1.0.14.dist-info/WHEEL
curc-1.0.14.dist-info/entry_points.txt
curc-1.0.14.dist-info/licenses/LICENSE
curc-1.0.14.dist-info/RECORD
